nex_weaver-1.1.1.dist-info/licenses/LICENSE
weaver/__init__.py
weaver/_http.py
weaver/_utils.py
weaver/cli.py
weaver/config.py
weaver/operations.py
weaver/sampling_client.py
weaver/service_client.py
weaver/training_client.py
weaver/types/__init__.py
weaver/types/datum.py
weaver/types/lora_config.py
weaver/types/model_input.py
weaver/types/optim.py
weaver/types/sampling.py
weaver/types/tensor.py
nex_weaver-1.1.1.dist-info/METADATA
nex_weaver-1.1.1.dist-info/WHEEL
nex_weaver-1.1.1.dist-info/entry_points.txt
nex_weaver-1.1.1.dist-info/top_level.txt
nex_weaver-1.1.1.dist-info/RECORD
