Metadata-Version: 2.4
Name: nex-weaver
Version: 1.1.1
Summary: Python SDK for the Weaver platform
Author: Nex-AGI
License: Proprietary
Requires-Python: >=3.10
License-File: LICENSE
Requires-Dist: httpx<0.30,>=0.27
Requires-Dist: socksio>=1.0.0
Requires-Dist: pydantic<3,>=2.6
Requires-Dist: torch<3,>=2.3
Requires-Dist: transformers<5,>=4.40
Requires-Dist: typing-extensions<5,>=4.8
Requires-Dist: click<9,>=8.1
Requires-Dist: rich<14,>=13.0
Provides-Extra: dev
Requires-Dist: pytest>=7; extra == "dev"
Requires-Dist: pytest-cov>=4.0; extra == "dev"
Requires-Dist: ruff>=0.4; extra == "dev"
Requires-Dist: black>=25.1.0; extra == "dev"
Requires-Dist: isort>=5.13; extra == "dev"
Requires-Dist: pylint>=3.0; extra == "dev"
Requires-Dist: mypy>=1.16; extra == "dev"
Requires-Dist: pre-commit>=3.0; extra == "dev"
Dynamic: license-file
